ooregex/__init__.py
ooregex/ooregex.py
ooregex-0.2.0.dist-info/LICENSE
ooregex-0.2.0.dist-info/WHEEL
ooregex-0.2.0.dist-info/METADATA
ooregex-0.2.0.dist-info/RECORD
