Metadata-Version: 2.1
Name: ooregex
Version: 0.2.0
Summary: A simple, object-oriented, regular expression generator.
Home-page: https://github.com/TitaniumBrain/ooregex
Keywords: regex,object oriented
Author: Titanium Brain
Author-email: titaniumbrain@vivaldi.net
Requires-Python: >=3.7,<4.0
Classifier: Programming Language :: Python :: 3
Classifier: Programming Language :: Python :: 3.7
Classifier: Programming Language :: Python :: 3.8
Classifier: Programming Language :: Python :: 3.9
Classifier: Programming Language :: Python :: 3.10
Classifier: Programming Language :: Python :: 3.11
Project-URL: Documentation, https://github.com/TitaniumBrain/ooregex/docs/
